README.md
setup.py
planter/__init__.py
planter.egg-info/PKG-INFO
planter.egg-info/SOURCES.txt
planter.egg-info/dependency_links.txt
planter.egg-info/top_level.txt
test/test_all.py